mattermost_client/__init__.py
mattermost_client/client.py
mattermost_client/tests.py
mattermost_client_py-0.1.2.dist-info/licenses/LICENSE
mattermost_client_py-0.1.2.dist-info/METADATA
mattermost_client_py-0.1.2.dist-info/WHEEL
mattermost_client_py-0.1.2.dist-info/top_level.txt
mattermost_client_py-0.1.2.dist-info/RECORD
