Metadata-Version: 2.4
Name: mattermost-client-py
Version: 0.1.2
Summary: A Python client for Mattermost incoming webhooks.
Author-email: Anshul Thakur <anshulthakurjourneyendless@gmail.com>
License-Expression: MIT
Project-URL: Homepage, https://github.com/anshulthakur/mm-py-webhooks
Project-URL: Bug Tracker, https://github.com/anshulthakur/mm-py-webhooks/issues
Requires-Python: >=3.7
License-File: LICENSE
Requires-Dist: requests
Requires-Dist: aiohttp
Dynamic: license-file
